aconf/__init__.py
aconf-1.0.1.dist-info/METADATA
aconf-1.0.1.dist-info/WHEEL
aconf-1.0.1.dist-info/top_level.txt
aconf-1.0.1.dist-info/RECORD
