Metadata-Version: 2.1
Name: aconf
Version: 1.0.1
Summary: Global memory-based configuration.
Home-page: https://github.com/synchronizing/aconf
Author: Felipe Faria
License: UNKNOWN
Platform: UNKNOWN
Classifier: Programming Language :: Python :: 3
Classifier: License :: OSI Approved :: MIT License
Classifier: Operating System :: OS Independent
Requires-Python: >=3.6
Requires-Dist: namedtupled (>=0.3.3)
